{"name": "uyg", "pixels": [{"name": "pix[0]", "value": "#000000"}, {"name": "pix[1]", "value": "#000000"}, {"name": "pix[2]", "value": "#000000"}, {"name": "pix[3]", "value": "#923a3a"}, {"name": "pix[4]", "value": "#923a3a"}, {"name": "pix[5]", "value": "#923a3a"}, {"name": "pix[6]", "value": "#923a3a"}, {"name": "pix[7]", "value": "#923a3a"}, {"name": "pix[8]", "value": "#923a3a"}, {"name": "pix[9]", "value": "#923a3a"}, {"name": "pix[10]", "value": "#923a3a"}, {"name": "pix[11]", "value": "#923a3a"}, {"name": "pix[12]", "value": "#923a3a"}, {"name": "pix[13]", "value": "#923a3a"}, {"name": "pix[14]", "value": "#923a3a"}, {"name": "pix[15]", "value": "#923a3a"}, {"name": "pix[16]", "value": "#ffffff"}, {"name": "pix[17]", "value": "#923a3a"}, {"name": "pix[18]", "value": "#923a3a"}, {"name": "pix[19]", "value": "#923a3a"}, {"name": "pix[20]", "value": "#923a3a"}, {"name": "pix[21]", "value": "#923a3a"}, {"name": "pix[22]", "value": "#923a3a"}, {"name": "pix[23]", "value": "#923a3a"}, {"name": "pix[24]", "value": "#923a3a"}, {"name": "pix[25]", "value": "#923a3a"}, {"name": "pix[26]", "value": "#923a3a"}, {"name": "pix[27]", "value": "#923a3a"}, {"name": "pix[28]", "value": "#923a3a"}, {"name": "pix[29]", "value": "#923a3a"}, {"name": "pix[30]", "value": "#923a3a"}, {"name": "pix[31]", "value": "#923a3a"}, {"name": "pix[32]", "value": "#923a3a"}, {"name": "pix[33]", "value": "#923a3a"}, {"name": "pix[34]", "value": "#923a3a"}, {"name": "pix[35]", "value": "#923a3a"}, {"name": "pix[36]", "value": "#923a3a"}, {"name": "pix[37]", "value": "#923a3a"}, {"name": "pix[38]", "value": "#923a3a"}, {"name": "pix[39]", "value": "#923a3a"}, {"name": "pix[40]", "value": "#923a3a"}, {"name": "pix[41]", "value": "#923a3a"}, {"name": "pix[42]", "value": "#923a3a"}, {"name": "pix[43]", "value": "#923a3a"}, {"name": "pix[44]", "value": "#923a3a"}, {"name": "pix[45]", "value": "#923a3a"}, {"name": "pix[46]", "value": "#923a3a"}, {"name": "pix[47]", "value": "#923a3a"}, {"name": "pix[48]", "value": "#923a3a"}, {"name": "pix[49]", "value": "#923a3a"}, {"name": "pix[50]", "value": "#923a3a"}, {"name": "pix[51]", "value": "#923a3a"}, {"name": "pix[52]", "value": "#923a3a"}, {"name": "pix[53]", "value": "#923a3a"}, {"name": "pix[54]", "value": "#923a3a"}, {"name": "pix[55]", "value": "#923a3a"}, {"name": "pix[56]", "value": "#923a3a"}, {"name": "pix[57]", "value": "#923a3a"}, {"name": "pix[58]", "value": "#923a3a"}, {"name": "pix[59]", "value": "#923a3a"}, {"name": "pix[60]", "value": "#923a3a"}, {"name": "pix[61]", "value": "#923a3a"}, {"name": "pix[62]", "value": "#923a3a"}, {"name": "pix[63]", "value": "#923a3a"}, {"name": "pix[64]", "value": "#923a3a"}, {"name": "pix[65]", "value": "#923a3a"}, {"name": "pix[66]", "value": "#923a3a"}, {"name": "pix[67]", "value": "#923a3a"}, {"name": "pix[68]", "value": "#923a3a"}, {"name": "pix[69]", "value": "#923a3a"}, {"name": "pix[70]", "value": "#923a3a"}, {"name": "pix[71]", "value": "#923a3a"}, {"name": "pix[72]", "value": "#923a3a"}, {"name": "pix[73]", "value": "#923a3a"}, {"name": "pix[74]", "value": "#923a3a"}, {"name": "pix[75]", "value": "#923a3a"}, {"name": "pix[76]", "value": "#923a3a"}, {"name": "pix[77]", "value": "#923a3a"}, {"name": "pix[78]", "value": "#923a3a"}, {"name": "pix[79]", "value": "#923a3a"}, {"name": "pix[80]", "value": "#923a3a"}, {"name": "pix[81]", "value": "#923a3a"}, {"name": "pix[82]", "value": "#923a3a"}, {"name": "pix[83]", "value": "#923a3a"}, {"name": "pix[84]", "value": "#923a3a"}, {"name": "pix[85]", "value": "#923a3a"}, {"name": "pix[86]", "value": "#923a3a"}, {"name": "pix[87]", "value": "#923a3a"}, {"name": "pix[88]", "value": "#923a3a"}, {"name": "pix[89]", "value": "#923a3a"}, {"name": "pix[90]", "value": "#923a3a"}, {"name": "pix[91]", "value": "#923a3a"}, {"name": "pix[92]", "value": "#923a3a"}, {"name": "pix[93]", "value": "#923a3a"}, {"name": "pix[94]", "value": "#923a3a"}, {"name": "pix[95]", "value": "#923a3a"}, {"name": "pix[96]", "value": "#923a3a"}, {"name": "pix[97]", "value": "#923a3a"}, {"name": "pix[98]", "value": "#923a3a"}, {"name": "pix[99]", "value": "#923a3a"}, {"name": "pix[100]", "value": "#923a3a"}, {"name": "pix[101]", "value": "#923a3a"}, {"name": "pix[102]", "value": "#923a3a"}, {"name": "pix[103]", "value": "#923a3a"}, {"name": "pix[104]", "value": "#923a3a"}, {"name": "pix[105]", "value": "#923a3a"}, {"name": "pix[106]", "value": "#923a3a"}, {"name": "pix[107]", "value": "#923a3a"}, {"name": "pix[108]", "value": "#923a3a"}, {"name": "pix[109]", "value": "#923a3a"}, {"name": "pix[110]", "value": "#923a3a"}, {"name": "pix[111]", "value": "#923a3a"}, {"name": "pix[112]", "value": "#923a3a"}, {"name": "pix[113]", "value": "#923a3a"}, {"name": "pix[114]", "value": "#923a3a"}, {"name": "pix[115]", "value": "#923a3a"}, {"name": "pix[116]", "value": "#923a3a"}, {"name": "pix[117]", "value": "#923a3a"}, {"name": "pix[118]", "value": "#923a3a"}, {"name": "pix[119]", "value": "#923a3a"}, {"name": "pix[120]", "value": "#923a3a"}, {"name": "pix[121]", "value": "#923a3a"}, {"name": "pix[122]", "value": "#923a3a"}, {"name": "pix[123]", "value": "#923a3a"}, {"name": "pix[124]", "value": "#923a3a"}, {"name": "pix[125]", "value": "#923a3a"}, {"name": "pix[126]", "value": "#923a3a"}, {"name": "pix[127]", "value": "#923a3a"}, {"name": "pix[128]", "value": "#923a3a"}, {"name": "pix[129]", "value": "#923a3a"}, {"name": "pix[130]", "value": "#923a3a"}, {"name": "pix[131]", "value": "#923a3a"}, {"name": "pix[132]", "value": "#923a3a"}, {"name": "pix[133]", "value": "#923a3a"}, {"name": "pix[134]", "value": "#923a3a"}, {"name": "pix[135]", "value": "#923a3a"}, {"name": "pix[136]", "value": "#923a3a"}, {"name": "pix[137]", "value": "#923a3a"}, {"name": "pix[138]", "value": "#923a3a"}, {"name": "pix[139]", "value": "#923a3a"}, {"name": "pix[140]", "value": "#923a3a"}, {"name": "pix[141]", "value": "#923a3a"}, {"name": "pix[142]", "value": "#923a3a"}, {"name": "pix[143]", "value": "#923a3a"}, {"name": "pix[144]", "value": "#923a3a"}, {"name": "pix[145]", "value": "#923a3a"}, {"name": "pix[146]", "value": "#923a3a"}, {"name": "pix[147]", "value": "#923a3a"}, {"name": "pix[148]", "value": "#923a3a"}, {"name": "pix[149]", "value": "#923a3a"}, {"name": "pix[150]", "value": "#923a3a"}, {"name": "pix[151]", "value": "#923a3a"}, {"name": "pix[152]", "value": "#923a3a"}, {"name": "pix[153]", "value": "#923a3a"}, {"name": "pix[154]", "value": "#923a3a"}, {"name": "pix[155]", "value": "#923a3a"}, {"name": "pix[156]", "value": "#923a3a"}, {"name": "pix[157]", "value": "#923a3a"}, {"name": "pix[158]", "value": "#923a3a"}, {"name": "pix[159]", "value": "#923a3a"}, {"name": "pix[160]", "value": "#923a3a"}, {"name": "pix[161]", "value": "#923a3a"}, {"name": "pix[162]", "value": "#923a3a"}, {"name": "pix[163]", "value": "#923a3a"}, {"name": "pix[164]", "value": "#923a3a"}, {"name": "pix[165]", "value": "#923a3a"}, {"name": "pix[166]", "value": "#923a3a"}, {"name": "pix[167]", "value": "#923a3a"}, {"name": "pix[168]", "value": "#923a3a"}, {"name": "pix[169]", "value": "#923a3a"}, {"name": "pix[170]", "value": "#923a3a"}, {"name": "pix[171]", "value": "#923a3a"}, {"name": "pix[172]", "value": "#923a3a"}, {"name": "pix[173]", "value": "#923a3a"}, {"name": "pix[174]", "value": "#923a3a"}, {"name": "pix[175]", "value": "#923a3a"}, {"name": "pix[176]", "value": "#923a3a"}, {"name": "pix[177]", "value": "#923a3a"}, {"name": "pix[178]", "value": "#923a3a"}, {"name": "pix[179]", "value": "#923a3a"}, {"name": "pix[180]", "value": "#923a3a"}, {"name": "pix[181]", "value": "#923a3a"}, {"name": "pix[182]", "value": "#923a3a"}, {"name": "pix[183]", "value": "#923a3a"}, {"name": "pix[184]", "value": "#923a3a"}, {"name": "pix[185]", "value": "#923a3a"}, {"name": "pix[186]", "value": "#923a3a"}, {"name": "pix[187]", "value": "#923a3a"}, {"name": "pix[188]", "value": "#923a3a"}, {"name": "pix[189]", "value": "#923a3a"}, {"name": "pix[190]", "value": "#923a3a"}, {"name": "pix[191]", "value": "#923a3a"}, {"name": "pix[192]", "value": "#923a3a"}, {"name": "pix[193]", "value": "#923a3a"}, {"name": "pix[194]", "value": "#923a3a"}, {"name": "pix[195]", "value": "#923a3a"}, {"name": "pix[196]", "value": "#923a3a"}, {"name": "pix[197]", "value": "#923a3a"}, {"name": "pix[198]", "value": "#923a3a"}, {"name": "pix[199]", "value": "#923a3a"}, {"name": "pix[200]", "value": "#923a3a"}, {"name": "pix[201]", "value": "#923a3a"}, {"name": "pix[202]", "value": "#923a3a"}, {"name": "pix[203]", "value": "#923a3a"}, {"name": "pix[204]", "value": "#923a3a"}, {"name": "pix[205]", "value": "#923a3a"}, {"name": "pix[206]", "value": "#923a3a"}, {"name": "pix[207]", "value": "#923a3a"}, {"name": "pix[208]", "value": "#923a3a"}, {"name": "pix[209]", "value": "#923a3a"}, {"name": "pix[210]", "value": "#923a3a"}, {"name": "pix[211]", "value": "#923a3a"}, {"name": "pix[212]", "value": "#923a3a"}, {"name": "pix[213]", "value": "#923a3a"}, {"name": "pix[214]", "value": "#923a3a"}, {"name": "pix[215]", "value": "#923a3a"}, {"name": "pix[216]", "value": "#923a3a"}, {"name": "pix[217]", "value": "#923a3a"}, {"name": "pix[218]", "value": "#923a3a"}, {"name": "pix[219]", "value": "#923a3a"}, {"name": "pix[220]", "value": "#923a3a"}, {"name": "pix[221]", "value": "#923a3a"}, {"name": "pix[222]", "value": "#923a3a"}, {"name": "pix[223]", "value": "#923a3a"}, {"name": "pix[224]", "value": "#923a3a"}, {"name": "pix[225]", "value": "#923a3a"}, {"name": "pix[226]", "value": "#923a3a"}, {"name": "pix[227]", "value": "#923a3a"}, {"name": "pix[228]", "value": "#923a3a"}, {"name": "pix[229]", "value": "#923a3a"}, {"name": "pix[230]", "value": "#923a3a"}, {"name": "pix[231]", "value": "#923a3a"}, {"name": "pix[232]", "value": "#923a3a"}, {"name": "pix[233]", "value": "#923a3a"}, {"name": "pix[234]", "value": "#923a3a"}, {"name": "pix[235]", "value": "#923a3a"}, {"name": "pix[236]", "value": "#923a3a"}, {"name": "pix[237]", "value": "#923a3a"}, {"name": "pix[238]", "value": "#923a3a"}, {"name": "pix[239]", "value": "#923a3a"}, {"name": "pix[240]", "value": "#923a3a"}, {"name": "pix[241]", "value": "#923a3a"}, {"name": "pix[242]", "value": "#923a3a"}, {"name": "pix[243]", "value": "#923a3a"}, {"name": "pix[244]", "value": "#923a3a"}, {"name": "pix[245]", "value": "#923a3a"}, {"name": "pix[246]", "value": "#923a3a"}, {"name": "pix[247]", "value": "#923a3a"}, {"name": "pix[248]", "value": "#923a3a"}, {"name": "pix[249]", "value": "#923a3a"}, {"name": "pix[250]", "value": "#923a3a"}, {"name": "pix[251]", "value": "#923a3a"}, {"name": "pix[252]", "value": "#923a3a"}, {"name": "pix[253]", "value": "#923a3a"}, {"name": "pix[254]", "value": "#923a3a"}, {"name": "pix[255]", "value": "#923a3a"}]}